distinct_keywords/__init__.py
distinct_keywords/keywords.py
distinct_keywords-0.29.dist-info/LICENSE
distinct_keywords-0.29.dist-info/METADATA
distinct_keywords-0.29.dist-info/WHEEL
distinct_keywords-0.29.dist-info/top_level.txt
distinct_keywords-0.29.dist-info/RECORD
