Metadata-Version: 2.1
Name: distinct-keywords
Version: 0.29
Summary: UNKNOWN
Home-page: https://github.com/sahyagiri/DistinctKeywords
Author: Gireesan Namboothiri
Author-email: sahyagiri@gmail.com
License: UNKNOWN
Project-URL: Bug Tracker, https://github.com/sahyagiri/DistinctKeywords/issues
Keywords: hilbert_curve,word2vec,key phrase extraction
Platform: UNKNOWN
Classifier: Programming Language :: Python :: 3
Classifier: License :: OSI Approved :: MIT License
Classifier: Operating System :: OS Independent
Requires-Python: >=3.6
License-File: LICENSE
Requires-Dist: datrie
Requires-Dist: flashtext
Requires-Dist: gensim
Requires-Dist: joblib
Requires-Dist: nltk
Requires-Dist: scikit-learn
Requires-Dist: sortedcontainers
Requires-Dist: spacy
